plenty/__init__.py
plenty/_emoji_codes.py
plenty/_loop.py
plenty/_table.py
plenty/box.py
plenty/color.py
plenty/console.py
plenty/const.py
plenty/effect.py
plenty/emoji.py
plenty/errors.py
plenty/info.py
plenty/markup.py
plenty/ratio.py
plenty/render.py
plenty/segment.py
plenty/str_utils.py
plenty/style.py
plenty/table.py
plenty-1.0.2.dist-info/LICENSE
plenty-1.0.2.dist-info/METADATA
plenty-1.0.2.dist-info/WHEEL
plenty-1.0.2.dist-info/top_level.txt
plenty-1.0.2.dist-info/RECORD
